rlutils/__init__.py
rlutils/utils.py
rlutils/agent/Agent.py
rlutils/agent/QLearning.py
rlutils/agent/StateRepresentationWrapperAgent.py
rlutils/agent/VIAgent.py
rlutils/agent/ValueFunctionAgent.py
rlutils/agent/ZeroValueAgent.py
rlutils/agent/__init__.py
rlutils/algorithm/__init__.py
rlutils/algorithm/vi.py
rlutils/basisfunction/ActionTiledBasisFunction.py
rlutils/basisfunction/__init__.py
rlutils/data/__init__.py
rlutils/data/buffer_sampler.py
rlutils/data/simulate.py
rlutils/data/transition_buffer.py
rlutils/environment/PuddleWorld.py
rlutils/environment/TabularMDP.py
rlutils/environment/__init__.py
rlutils/environment/gridworld.py
rlutils/logging/LoggerEpisodeLength.py
rlutils/logging/LoggerTotalReward.py
rlutils/logging/LoggerTrajectory.py
rlutils/logging/__init__.py
rlutils/plot/ColorMap.py
rlutils/plot/__init__.py
rlutils/plot/gridworld_policy.py
rlutils/plot/gridworld_state_action_map.py
rlutils/plot/mean_with_max_min.py
rlutils/plot/mean_with_sem.py
rlutils/plot/utils.py
rlutils/policy/ActionSequencePolicy.py
rlutils/policy/EGreedyPolicy.py
rlutils/policy/GreedyPolicy.py
rlutils/policy/Policy.py
rlutils/policy/UniformRandomPolicy.py
rlutils/policy/ValuePolicy.py
rlutils/policy/__init__.py
rlutils/schedule/LinearInterpolatedVariableSchedule.py
rlutils/schedule/VariableSchedule.py
rlutils/schedule/__init__.py
rlutils-0.0.2.dist-info/LICENSE
rlutils-0.0.2.dist-info/METADATA
rlutils-0.0.2.dist-info/WHEEL
rlutils-0.0.2.dist-info/top_level.txt
rlutils-0.0.2.dist-info/RECORD
