Metadata-Version: 2.1
Name: rlutils
Version: 0.0.2
Summary: rlutils: A utility package for implementing reinforcement learning simulations.
Home-page: https://github.com/lucaslehnert/rlutils
Author: The rlutils authors
Author-email: lucas_lehnert@brown.edu
License: UNKNOWN
Platform: UNKNOWN
Classifier: Programming Language :: Python :: 3
Classifier: License :: OSI Approved :: MIT License
Classifier: Operating System :: OS Independent
Requires-Python: >=3.5
Requires-Dist: numpy (>=1.17)
Requires-Dist: gym (>=0.12.5)
Requires-Dist: matplotlib
Requires-Dist: pygame (==1.9.6)
Requires-Dist: PyYAML (==5.1)
Requires-Dist: colorlover (==0.3.0)
Requires-Dist: plotly (>=4.4.1)
